yonlu/__init__.py
yonlu/bert/__init__.py
yonlu/bert/att_all_you_need.py
yonlu/bert/attention_test.py
yonlu/bert/bart_classification.py
yonlu/bert/bart_mask_filling.py
yonlu/bert/bart_nmt.py
yonlu/bert/bart_summarizer.py
yonlu/bert/bert_classification_model.py
yonlu/bert/bert_dataset.py
yonlu/bert/bert_predictor.py
yonlu/bert/bert_trainer.py
yonlu/bert/bert_util.py
yonlu/bert/gpt3.py
yonlu/bert/load_kobert_model.py
yonlu/bert/tokenization_hanbert.py
yonlu/bert/tokenization_kobert.py
yonlu/convAI/__init__.py
yonlu/convAI/bert_mini_chatbot.py
yonlu/convAI/chatbot_trainer.py
yonlu/convAI/chatbot_utils.py
yonlu/convAI/example_entry.py
yonlu/convAI/export_question_embeddings.py
yonlu/convAI/gpt2_chitchat_trainer.py
yonlu/convAI/interact.py
yonlu/convAI/test_special_tokens.py
yonlu/data_utils/__init__.py
yonlu/data_utils/ner_dataset.py
yonlu/data_utils/pad_sequence.py
yonlu/data_utils/relation_dataset.py
yonlu/data_utils/translation_dataset.py
yonlu/data_utils/util.py
yonlu/data_utils/utils.py
yonlu/data_utils/vocab_tokenizer.py
yonlu/examples/__init__.py
yonlu/examples/app.py
yonlu/examples/bart_summarization_test.py
yonlu/examples/bert_en_word_embeddings.py
yonlu/examples/bert_ko_word_embeddings.py
yonlu/examples/bert_sentiment_predictor.py
yonlu/examples/bert_sentiment_trainer.py
yonlu/examples/bpe.py
yonlu/examples/chitchat.py
yonlu/examples/convert_unicode.py
yonlu/examples/coqa_predictor.py
yonlu/examples/dialogpt_example.py
yonlu/examples/doc2vec_clustering.py
yonlu/examples/doc2vec_tester.py
yonlu/examples/doc2vec_trainer.py
yonlu/examples/elastic_search.py
yonlu/examples/elastic_search_embeddings.py
yonlu/examples/electra_test.py
yonlu/examples/fasttext_tester.py
yonlu/examples/fasttext_trainer.py
yonlu/examples/glove_tester.py
yonlu/examples/gpt2_example1.py
yonlu/examples/gpt2_mnt.py
yonlu/examples/gpt2_test.py
yonlu/examples/gpt3_chatbot.py
yonlu/examples/gpt_embeddings.py
yonlu/examples/gpt_fragments.py
yonlu/examples/kogpt2_chat_trainer.py
yonlu-1.1.22.dist-info/LICENSE
yonlu-1.1.22.dist-info/METADATA
yonlu-1.1.22.dist-info/WHEEL
yonlu-1.1.22.dist-info/top_level.txt
yonlu-1.1.22.dist-info/RECORD
